{"id":"index.html","dependencies":[{"name":"D:\\cygwin\\home\\Leonardo\\Workspace\\fmag\\package.json","includedInParent":true,"mtime":1539122502566},{"name":"./app.js","dynamic":true,"parent":"D:\\cygwin\\home\\Leonardo\\Workspace\\fmag\\index.html","resolved":"D:\\cygwin\\home\\Leonardo\\Workspace\\fmag\\app.js"}],"generated":{"html":"<!DOCTYPE html>\r\n<html lang=\"en\">\r\n<head>\r\n  <meta charset=\"UTF-8\">\r\n  <meta name=\"viewport\" content=\"width=device-width, initial-scale=1.0\">\r\n  <meta http-equiv=\"X-UA-Compatible\" content=\"ie=edge\">\r\n  <title>FMag</title>\r\n  <style>\r\n    body, html {\r\n      margin: 0;\r\n      padding: 0;\r\n      overflow: hidden;\r\n    }\r\n  </style>\r\n</head>\r\n<body>\r\n  \r\n  <canvas id=\"world\"></canvas>\r\n\r\n  <script src=\"/2c2cf1fde3d0ce869647898b54601421.js\"></script>\r\n\r\n</body>\r\n</html>"},"hash":"b0e6cca43a17227d043b6b78a2aca788","cacheData":{}}